carbonplan_trace/__init__.py
carbonplan_trace/constants.py
carbonplan_trace/metadata.py
carbonplan_trace/tiles.py
carbonplan_trace/utils.py
carbonplan_trace/fire/__init__.py
carbonplan_trace/fire/grid_viirs_workflow.py
carbonplan_trace/v0/__init__.py
carbonplan_trace/v0/core.py
carbonplan_trace/v0/workflow.py
carbonplan_trace/v0/data/__init__.py
carbonplan_trace/v0/data/catalog.yaml
carbonplan_trace/v0/data/load.py
carbonplan_trace/v1/__init__.py
carbonplan_trace/v1/biomass_rollup.py
carbonplan_trace/v1/change_point_detection.py
carbonplan_trace/v1/glas_allometric_eq.py
carbonplan_trace/v1/glas_extract.py
carbonplan_trace/v1/glas_height_metrics.py
carbonplan_trace/v1/glas_preprocess.py
carbonplan_trace/v1/inference.py
carbonplan_trace/v1/landsat_preprocess.py
carbonplan_trace/v1/load.py
carbonplan_trace/v1/model.py
carbonplan_trace/v1/postprocess.py
carbonplan_trace/v1/tests.py
carbonplan_trace/v1/training_prep.py
carbonplan_trace/v1/utils.py
carbonplan_trace-0.4.0.dist-info/LICENSE
carbonplan_trace-0.4.0.dist-info/METADATA
carbonplan_trace-0.4.0.dist-info/WHEEL
carbonplan_trace-0.4.0.dist-info/top_level.txt
carbonplan_trace-0.4.0.dist-info/RECORD
