Metadata-Version: 2.1
Name: carbonplan-trace
Version: 0.4.0
Summary: tracking forest carbon emissions
Home-page: https://github.com/carbonplan/trace
Maintainer: Joe Hamman
Maintainer-email: joe@carbonplan.org
License: MIT
Keywords: carbon,data,climate,climatetrace
Platform: UNKNOWN
Requires-Python: >=3.7
Requires-Dist: awswrangler
Requires-Dist: carbonplan
Requires-Dist: dask[complete]
Requires-Dist: fsspec
Requires-Dist: google-cloud-storage
Requires-Dist: intake
Requires-Dist: intake-geopandas
Requires-Dist: intake-xarray
Requires-Dist: h5py
Requires-Dist: pandas
Requires-Dist: prefect
Requires-Dist: pytest
Requires-Dist: rasterio
Requires-Dist: scikit-learn
Requires-Dist: utm
Requires-Dist: xarray
Requires-Dist: zarr
